veritas/__init__.py
veritas/addtree_conversion.py
veritas/groot.py
veritas/kantchelian.py
veritas/lgbm_converter.py
veritas/robustness.py
veritas/sklearn_converter.py
veritas/smt.py
veritas/util.py
veritas/veritas_core.cp310-win_amd64.pyd
veritas/xgb_converter.py
veritas/z3backend.py
dtai_veritas-0.2.3.dist-info/LICENSE
dtai_veritas-0.2.3.dist-info/METADATA
dtai_veritas-0.2.3.dist-info/WHEEL
dtai_veritas-0.2.3.dist-info/top_level.txt
dtai_veritas-0.2.3.dist-info/RECORD
