Metadata-Version: 2.1
Name: dtai-veritas
Version: 0.2.3
Home-page: https://github.com/laudv/veritas
Author: Laurens Devos
Author-email: 
Maintainer: Laurens Devos
Maintainer-email: 
License: Apache-2.0
Requires-Python: >=3.8
License-File: LICENSE
Requires-Dist: numpy
